setup.py
configargparser/__init__.py
configargparser.egg-info/PKG-INFO
configargparser.egg-info/SOURCES.txt
configargparser.egg-info/dependency_links.txt
configargparser.egg-info/top_level.txt