Metadata-Version: 1.0
Name: configargparser
Version: 0.0.2
Summary: Parse arguments from anywhere
Home-page: https://github.com/mgilson/configargparser
Author: Matthew Gilson
Author-email: m.gilson1@gmail.com
License: MIT
Platform: UNKNOWN
